BlockScout/__init__.py
BlockScout/base.py
BlockScout/blast.py
BlockScout/eth.py
BlockScout/optimism.py
BlockScout/polygon.py
BlockScout/setup.py
BlockScoutSDK-1.0.0.dist-info/LICENSE
BlockScoutSDK-1.0.0.dist-info/METADATA
BlockScoutSDK-1.0.0.dist-info/WHEEL
BlockScoutSDK-1.0.0.dist-info/top_level.txt
BlockScoutSDK-1.0.0.dist-info/RECORD
