Metadata-Version: 2.1
Name: BlockScoutSDK
Version: 1.0.0
Summary: A python wrapper for the BlockScout eth,optimism, base, blast and polygon apis
Home-page: https://github.com/kbm9696/BlockScout-SDK
Author: Balamurugan
Author-email: kbala007.1996@gmail.com
License: GNU General Public License v3.0
Platform: UNKNOWN
License-File: LICENSE
Requires-Dist: requests
